odoo/addons/connector_search_engine/README.rst
odoo/addons/connector_search_engine/__init__.py
odoo/addons/connector_search_engine/__manifest__.py
odoo/addons/connector_search_engine/data/ir_action_data.xml
odoo/addons/connector_search_engine/data/ir_cron.xml
odoo/addons/connector_search_engine/data/queue_job_channel_data.xml
odoo/addons/connector_search_engine/data/queue_job_function_data.xml
odoo/addons/connector_search_engine/i18n/connector_search_engine.pot
odoo/addons/connector_search_engine/i18n/fr.po
odoo/addons/connector_search_engine/i18n/it.po
odoo/addons/connector_search_engine/models/__init__.py
odoo/addons/connector_search_engine/models/ir_actions.py
odoo/addons/connector_search_engine/models/se_backend.py
odoo/addons/connector_search_engine/models/se_binding.py
odoo/addons/connector_search_engine/models/se_index.py
odoo/addons/connector_search_engine/models/se_index_config.py
odoo/addons/connector_search_engine/models/se_indexable_record.py
odoo/addons/connector_search_engine/readme/CHANGES.rst
odoo/addons/connector_search_engine/readme/CONTRIBUTORS.rst
odoo/addons/connector_search_engine/readme/DESCRIPTION.rst
odoo/addons/connector_search_engine/readme/HISTORY.rst
odoo/addons/connector_search_engine/readme/INSTALL.rst
odoo/addons/connector_search_engine/readme/ROADMAP.rst
odoo/addons/connector_search_engine/readme/USAGE.rst
odoo/addons/connector_search_engine/readme/newsfragments/.gitignore
odoo/addons/connector_search_engine/security/connector_search_engine_security.xml
odoo/addons/connector_search_engine/security/ir.model.access.csv
odoo/addons/connector_search_engine/security/se_index_config.xml
odoo/addons/connector_search_engine/static/description/icon.png
odoo/addons/connector_search_engine/static/description/index.html
odoo/addons/connector_search_engine/tests/__init__.py
odoo/addons/connector_search_engine/tests/common.py
odoo/addons/connector_search_engine/tests/models.py
odoo/addons/connector_search_engine/tests/test_all.py
odoo_addon_connector_search_engine-16.0.1.1.0.2.dist-info/METADATA
odoo_addon_connector_search_engine-16.0.1.1.0.2.dist-info/WHEEL
odoo_addon_connector_search_engine-16.0.1.1.0.2.dist-info/top_level.txt
odoo_addon_connector_search_engine-16.0.1.1.0.2.dist-info/RECORD
