Metadata-Version: 2.1
Name: odoo-addon-connector_search_engine
Version: 16.0.1.1.0.2
Summary: Connector Search Engine
Home-page: https://github.com/OCA/search-engine
Author: Akretion,ACSONE SA/NV,Camptocamp,Odoo Community Association (OCA)
Author-email: support@odoo-community.org
License: AGPL-3
Classifier: Programming Language :: Python
Classifier: Framework :: Odoo
Classifier: Framework :: Odoo :: 16.0
Classifier: License :: OSI Approved :: GNU Affero General Public License v3
Requires-Python: >=3.10
Requires-Dist: odoo-addon-base-partition<16.1dev,>=16.0dev
Requires-Dist: odoo-addon-queue-job<16.1dev,>=16.0dev
Requires-Dist: odoo-addon-server-environment<16.1dev,>=16.0dev
Requires-Dist: odoo<16.1dev,>=16.0a
Requires-Dist: typing-extensions
Requires-Dist: unidecode
